Workbook

Sheet Cover
B2: HNW FINANCIAL PLANNING REPORT — MITCHELL FAMILY
B3: Private Wealth Management | Confidential | Prepared by: Vatsal Chavda, BCom Finance
B5: CLIENT PROFILE
B6: Client Names | C6: James Mitchell (Age 52) & Sarah Mitchell (Age 49)
B7: Occupation | C7: James: Orthopaedic Surgeon — St. Michael's Hospital | Sarah: Partner, Bay Street Law Firm
B8: Dependants | C8: Emma Mitchell (Age 19 — University) | Liam Mitchell (Age 16 — High School)
B9: Primary Residence | C9: Forest Hill, Toronto, Ontario
B10: Report Date | C10: April 2025
B11: Planning Horizon | C11: 30 Years — James targets retirement at Age 60 (2033); Sarah at Age 62 (2038)
B12: Primary Objectives | C12: Retirement income planning, tax minimization, estate transfer, children's education funding
B13: Risk Profile | C13: Balanced-Growth | Risk Score: 6.5 / 10 | Growth tilt with capital preservation focus
B15: WORKBOOK CONTENTS
B16: Net Worth Statement | C16: Complete asset and liability summary; net worth calculation with live SUM formulas
B17: Cash Flow Analysis | C17: Annual income, expenses, savings allocation, and surplus check formula
B18: Retirement Projections | C18: Compound growth projections for all portfolios; retirement income gap analysis
B19: Education Funding | C19: RESP growth projections for Emma and Liam; annual cost inflation with formulas
B20: Tax Optimization | C20: Marginal rate analysis, RRSP deduction benefit formulas, strategy recommendations
B21: Estate Plan Summary | C21: Estate inventory linked to Net Worth sheet; probate and tax-on-death calculations
B23: DISCLAIMER
B24: This report is a simulated financial planning case study prepared for portfolio demonstration purposes only. All client names, financial figures, and details are fictional. This document does not constitute financial, tax, legal, or investment advice.

Sheet NetWorthStatement
B1: NET WORTH STATEMENT — MITCHELL FAMILY
B3: ASSETS
B4: Asset Description | C4: Market Value (CAD) | D4: Notes
B5: Principal Residence — Forest Hill, Toronto | C5: 2850000 | D5: Estimated market value; mortgage below
B6: Vacation Property — Muskoka, ON | C6: 680000 | D6: Owned free and clear
B7: RRSP — James Mitchell | C7: 925000 | D7: Balanced-growth portfolio
B8: RRSP — Sarah Mitchell | C8: 710000 | D8: Balanced-growth portfolio
B9: TFSA — James Mitchell | C9: 95000 | D9: Fully maximized; equity-focused
B10: TFSA — Sarah Mitchell | C10: 95000 | D10: Fully maximized; equity-focused
B11: Non-Registered Investment Portfolio (Joint) | C11: 1450000 | D11: Balanced-growth allocation
B12: RESP — Emma & Liam (Combined) | C12: 148000 | D12: Growth-oriented
B13: DB Pension — James (Commuted Value Estimate) | C13: 1200000 | D13: Hospital pension plan
B14: Corporate Holdings — Sarah's Law Corp | C14: 880000 | D14: Retained earnings & passive investments
B15: Cash & Short-Term Savings | C15: 185000 | D15: Combined chequing and HISA
B16: Personal Property (Vehicles, Art, Jewelry) | C16: 220000 | D16: Estimated replacement value
B17: TOTAL ASSETS | C17: =SUM(C5:C16) -> 9438000
B19: LIABILITIES
B20: Liability Description | C20: Outstanding Balance (CAD) | D20: Notes
B21: Principal Residence Mortgage | C21: 420000 | D21: 20 years remaining; 4.89% fixed
B22: Home Equity Line of Credit (HELOC) | C22: 85000 | D22: Investment purpose; deductible interest
B23: Vehicle Loans — Combined | C23: 42000 | D23: Two vehicles outstanding
B24: Credit Cards / Short-Term Payables | C24: 8500 | D24: Paid in full monthly
B25: TOTAL LIABILITIES | C25: =SUM(C21:C24) -> 555500
B27: NET WORTH SUMMARY
B28: Total Assets | C28: =C17 -> 9438000
B29: Total Liabilities | C29: =C25 -> 555500
B30: NET WORTH — Mitchell Family | C30: =C28-C29 -> 8882500

Sheet CashFlowAnalysis
B1: ANNUAL CASH FLOW ANALYSIS — MITCHELL FAMILY
B3: GROSS ANNUAL INCOME
B4: Income Source | C4: Annual Amount (CAD) | D4: Notes
B5: James — Net Employment Income (after tax) | C5: 420000 | D5: T4; combined federal + Ontario marginal ~53.53%
B6: Sarah — Salary Draw from Law Corp | C6: 280000 | D6: Optimal salary extraction from corporation
B7: Sarah — Eligible Dividend from Law Corp | C7: 120000 | D7: Retained earnings distribution
B8: Non-Registered Portfolio — Dividends & Interest | C8: 52000 | D8: Mixed income type; partial dividend treatment
B9: Other Income | C9: 0 | D9: No additional income sources currently
B10: TOTAL NET INCOME | C10: =SUM(C5:C9) -> 872000
B12: ANNUAL LIVING & FIXED EXPENSES
B13: Expense Category | C13: Annual Amount (CAD) | D13: Notes
B14: Mortgage — Principal + Interest | C14: 42000 | D14: $3,500/month × 12
B15: Property Taxes — Primary Residence + Muskoka | C15: 28000 | D15: Combined annual assessment
B16: Household & Living Expenses | C16: 96000 | D16: Food, utilities, maintenance, subscriptions
B17: Children's Education & Activities | C17: 48000 | D17: Emma university + Liam tuition & activities
B18: Travel & Lifestyle | C18: 55000 | D18: Annual family travel budget
B19: Insurance Premiums — All Policies | C19: 38000 | D19: Life, disability, home, auto combined
B20: Vehicle Expenses | C20: 22000 | D20: Fuel, maintenance, insurance
B21: Charitable Donations | C21: 25000 | D21: Eligible for donation tax credit
B22: Personal & Discretionary Spending | C22: 40000 | D22: Clothing, dining, entertainment
B23: TOTAL ANNUAL EXPENSES | C23: =SUM(C14:C22) -> 394000
B25: ANNUAL SAVINGS & SURPLUS ALLOCATION
B26: Allocation | C26: Annual Amount (CAD) | D26: Notes
B27: Annual Cash Flow Surplus | C27: =C10-C23 -> 478000 | D27: Available for savings and investments
B28: RRSP Contributions — James | C28: 29000 | D28: Maximize annual contribution room
B29: RRSP Contributions — Sarah | C29: 27000 | D29: Maximize annual contribution room
B30: TFSA Contributions — James & Sarah (Combined) | C30: 14000 | D30: $7,000 each; fully maximized
B31: RESP Top-Up — Emma & Liam | C31: 8000 | D31: Annual top-up; CESG eligible
B32: Corporate Retained Earnings — Sarah's Law Corp | C32: 50000 | D32: Tax deferral at corporate rate
B33: Remaining Surplus — Non-Registered Investment | C33: =C27-SUM(C28:C32) -> 350000 | D33: Invested in non-registered portfolio
B34: TOTAL SAVINGS & INVESTMENTS | C34: =SUM(C28:C33) -> 478000
B35: VARIANCE CHECK (Surplus minus Allocated) | C35: =C27-C34 -> 0 | D35: Should equal $0 if fully allocated

Sheet RetirementProjections
B1: RETIREMENT INCOME PROJECTIONS — MITCHELL FAMILY
B3: KEY PLANNING ASSUMPTIONS
B4: Assumption | C4: Value | D4: Notes
B5: Current Age — James | C5: 52 | D5: Input: change to update all projections
B6: Current Age — Sarah | C6: 49
B7: Target Retirement Age — James | C7: 60 | D7: 8 years to retirement
B8: Target Retirement Age — Sarah | C8: 62 | D8: 13 years to retirement
B9: Years to James Retirement | C9: 8 | D9: B7-B5 = 60-52
B10: Pre-Retirement Portfolio Return (% p.a.) | C10: 0.065 | D10: 6.5% blended gross return
B11: Post-Retirement Portfolio Return (% p.a.) | C11: 0.045 | D11: 4.5% conservative return
B12: Inflation Rate (% p.a.) | C12: 0.025 | D12: 2.5% Bank of Canada target
B13: Target Annual Retirement Income (today $) | C13: 350000 | D13: Gross household income target
B14: Target Retirement Income (inflation-adjusted) | C14: 426441 | D14: 350000*(1.025)^8 = inflation-adjusted target
B16: PROJECTED PORTFOLIO VALUES AT RETIREMENT
B17: Portfolio / Account | C17: Current Value | D17: Growth Rate | E17: Years to Ret. | F17: Projected Value at Retirement
B18: RRSP — James | C18: 925000 | D18: 0.065 | E18: =B9 -> Years to James Retirement | F18: =C18*(1+0.065)^8 -> 1530871
B19: RRSP — Sarah | C19: 710000 | D19: 0.065 | E19: 13 | F19: =C19*(1+0.065)^13 -> 1609916.1
B20: TFSA — James (+ $7K/yr contributions) | C20: 95000 | D20: 0.065 | E20: =B9 -> Years to James Retirement | F20: =C20*(1+0.065)^8+7000*((1+0.065)^8-1)/0.065 -> 227762.58
B21: TFSA — Sarah (+ $7K/yr contributions) | C21: 95000 | D21: 0.065 | E21: 13 | F21: =C21*(1+0.065)^13+7000*((1+0.065)^13-1)/0.065 -> 351909.97
B22: Non-Registered Portfolio (+ $128K/yr) | C22: 1450000 | D22: 0.065 | E22: =B9 -> Years to James Retirement | F22: =C22*(1+0.065)^8+128000*((1+0.065)^8-1)/0.065 -> 3689581.4
B23: TOTAL PROJECTED PORTFOLIO AT RETIREMENT | C23: =SUM(F18:F22) -> 7410041
B25: ANNUAL RETIREMENT INCOME SOURCES
B26: Income Source | C26: Annual Income | D26: Tax Status | E26: % of Target | F26: Notes
B27: RRIF Drawdown — James (4% of RRIF balance) | C27: =F18*0.04 -> 61234.84 | D27: Fully Taxable | E27: =C27/426441 -> 0.1435951 | F27: Minimum RRIF drawdown rate at 71
B28: RRIF Drawdown — Sarah (4% of RRIF balance) | C28: =F19*0.04 -> 64396.645 | D28: Fully Taxable | E28: =C28/426441 -> 0.15100951
B29: DB Pension — James (Indexed) | C29: 110000 | D29: Fully Taxable | E29: =C29/426441 -> 0.25794893 | F29: $9,167/month; inflation-indexed
B30: CPP — James & Sarah (Combined, Age 65) | C30: 28872 | D30: Partially Taxable | E30: =C30/426441 -> 0.067704559 | F30: $1,306 + $1,100 × 12
B31: OAS — James & Sarah (Combined, Age 65) | C31: 16752 | D31: Fully Taxable | E31: =C31/426441 -> 0.039283277 | F31: $698 × 2 × 12
B32: Non-Registered Portfolio Income (3.5% yield) | C32: =F22*0.035 -> 129135.35 | D32: Dividends/Cap Gains | E32: =C32/426441 -> 0.30282113 | F32: Tax-preferred income
B33: TFSA Withdrawals (Supplemental) | C33: 30000 | D33: Tax-Free | E33: =C33/426441 -> 0.070349708 | F33: Flexible; no clawback impact
B34: Corporate Dividend Draw — Sarah's Law Corp | C34: 60000 | D34: Eligible Dividends | E34: =C34/426441 -> 0.14069942 | F34: Post-retirement distribution
B35: TOTAL PROJECTED RETIREMENT INCOME | C35: =SUM(C27:C34) -> 500390.83
B36: INCOME VS TARGET (Surplus / Gap) | C36: =C35-426441 -> 73949.832 | E36: =C35/426441 -> 1.1734116 | F36: Positive = surplus; Negative = shortfall

Sheet EducationFunding
B1: RESP & EDUCATION FUNDING PLAN — EMMA & LIAM MITCHELL
B3: ASSUMPTIONS
B4: Parameter | C4: Value | D4: Input Cell | E4: Notes
B5: Annual Tuition Inflation Rate | C5: 0.05 | D5: B5 | E5: 5% per year
B6: Emma — Current University Year | C6: 1 | D6: B6 | E6: Starting Year 1 (2025)
B7: Liam — Years Until University | C7: 2 | D7: B7 | E7: Starts 2027
B8: RESP Annual Return | C8: 0.055 | D8: B8 | E8: 5.5% growth assumed
B9: Current RESP Balance — Emma | C9: 80000 | D9: B9 | E9: Emma's allocated share
B10: Current RESP Balance — Liam | C10: 68000 | D10: B10 | E10: Liam's allocated share
B11: Annual CESG (20% on $2,500 each) | C11: 1000 | D11: B11 | E11: Combined government grant
B13: EMMA — 4-YEAR UNIVERSITY COST PROJECTION
B14: Cost Item | C14: Year 1 | D14: Year 2 | E14: Year 3 | F14: Year 4
B15: Tuition & Fees | C15: 28000 | D15: =C15*(1+0.05)^1 -> 29400 | E15: =C15*(1+0.05)^2 -> 30870 | F15: =C15*(1+0.05)^3 -> 32413.5
B16: Living Expenses | C16: 18000 | D16: =C16*(1+0.025)^1 -> 18450 | E16: =C16*(1+0.025)^2 -> 18911.25 | F16: =C16*(1+0.025)^3 -> 19384.031
B17: Books & Supplies | C17: 2500 | D17: =C17*(1+0.02)^1 -> 2550 | E17: =C17*(1+0.02)^2 -> 2601 | F17: =C17*(1+0.02)^3 -> 2653.02
B18: Total Annual Cost | C18: Year 1 | D18: Year 2 | E18: Year 3 | F18: Year 4
B19: Total Cost per Year | C19: =SUM(C15:C17) -> 48500 | D19: =SUM(D15:D17) -> 50400 | E19: =SUM(E15:E17) -> 52382.25 | F19: =SUM(F15:F17) -> 54450.551
B20: RESP Withdrawal Available | C20: 20000 | D20: 20000 | E20: 20000 | F20: 20000
B21: Parental Contribution Required | C21: =C19-C20 -> 28500 | D21: =D19-D20 -> 30400 | E21: =E19-E20 -> 32382.25 | F21: =F19-F20 -> 34450.551
B23: RESP GROWTH PROJECTION
B24: RESP Item | C24: Emma | D24: Liam | E24: Combined | F24: Notes
B25: Current RESP Balance | C25: 80000 | D25: 68000 | E25: =C25+D25 -> 148000 | F25: Input values above
B26: RESP Value at Start of Studies | C26: =C25*(1+0.055)^1 -> 84400 | D26: =D25*(1+0.055)^2 -> 75685.7 | E26: =C26+D26 -> 160085.7 | F26: FV with CESG reinvested
B27: Total CESG (Estimated — 4 years) | C27: 2000 | D27: 2000 | E27: =C27+D27 -> 4000 | F27: $500 each per year
B28: Projected Total RESP at Completion | C28: =C26+C27 -> 86400 | D28: =D26+D27 -> 77685.7 | E28: =C28+D28 -> 164085.7
B29: Total University Cost (4 years) | C29: =C19+D19+E19+F19 -> 205732.8 | F29: Emma only
B30: Total Parental Contribution Required | C30: =C29-C28 -> 119332.8 | F30: Emma only; Liam calculated separately

Sheet TaxOptimization
B1: TAX OPTIMIZATION ANALYSIS — MITCHELL FAMILY
B3: MARGINAL RATE INPUTS (ONTARIO 2025)
B4: Tax Input | C4: James | D4: Sarah
B5: Gross Taxable Income | C5: 800000 | D5: 620000
B6: Federal + Ontario Combined Marginal Rate | C6: 0.5353 | D6: 0.5353
B7: Estimated Effective Tax Rate | C7: 0.382 | D7: 0.348
B8: RRSP Contribution | C8: 29000 | D8: 27000
B9: RRSP Marginal Tax Deduction Benefit | C9: =C8*C7 -> 11078 | D9: =D8*D7 -> 9396
B10: TFSA Annual Contribution | C10: 7000 | D10: 7000
B11: Combined Household Tax Saving — RRSP | C11: =C9+D9 -> 20474
B13: TAX STRATEGY RECOMMENDATIONS
B14: Strategy | C14: Priority | D14: Action Required
B15: Maximize RRSP — James & Sarah (Annual) | C15: HIGH | D15: =C8 & " + " & D8 & " = $" & TEXT(C8+D8,"#,##0") & " total contribution" -> 29000 + 27000 = $56,000 total contribution
B16: Spousal RRSP — James contributes to Sarah's | C16: HIGH | D16: Equalizes retirement income; reduces combined marginal rate at drawdown
B17: TFSA Maximization — Both Parties | C17: HIGH | D17: $7,000 each annually; invest in highest-growth assets; tax-free compounding
B18: Income Splitting — Sarah's Corporation | C18: HIGH | D18: Pay salary to James for admin services rendered to law corp; must be reasonable
B19: Corporate Passive Investment Management | C19: HIGH | D19: Retain earnings below SBD limit ($500K); invest at corporate rate for deferral advantage
B20: Capital Gains Harvesting — Non-Registered | C20: MEDIUM | D20: Annual Q4 review; harvest losses to offset gains; maintain overall allocation
B21: Charitable Donation Bundling | C21: MEDIUM | D21: Bundle 2-3 years of donations in single tax year to maximize federal+Ontario tax credit

Sheet EstatePlanSummary
B1: ESTATE PLAN SUMMARY — MITCHELL FAMILY
B3: ESTATE ASSET INVENTORY
B4: Asset / Consideration | C4: Estimated Value | D4: Disposition / Notes
B5: Principal Residence (Net of Mortgage) | C5: =NetWorthStatement!C5-NetWorthStatement!C19 -> 2850000 | D5: Primary beneficiary: surviving spouse
B6: Vacation Property — Muskoka | C6: =NetWorthStatement!C6 -> 680000 | D6: Designated to Emma and Liam equally
B7: RRSP/RRIF — James (Taxable on Death — Full Value) | C7: 925000 | D7: Spousal rollover; deferred on first death
B8: RRSP/RRIF — Sarah (Taxable on Death — Full Value) | C8: 710000 | D8: Spousal rollover; deferred on first death
B9: TFSA — James & Sarah (Tax-Free to Estate) | C9: 190000 | D9: Passes tax-free; successor holder designation
B10: Non-Registered Portfolio | C10: =NetWorthStatement!C11 -> 1450000 | D10: 50% deemed disposition on death for tax
B11: Corporate Holdings — Sarah's Law Corp | C11: =NetWorthStatement!C14 -> 880000 | D11: Estate freeze or share transfer recommended
B12: Life Insurance Death Benefit | C12: 2000000 | D12: Tax-free to named beneficiary
B13: Personal Property & Other | C13: =NetWorthStatement!C16 -> 220000 | D13: Distributed per Will
B14: ESTIMATED GROSS ESTATE VALUE | C14: =SUM(C5:C13) -> 9905000
B16: ESTIMATED PROBATE & TAX ON DEATH (Ontario)
B17: Item | C17: Estimated Amount | D17: Notes
B18: Ontario Probate Fee (Estate Administration Tax) | C18: =((C14-50000)*0.015)+250 -> 148075 | D18: 1.5% on estate value over $50,000
B19: Deemed Disposition — RRSP/RRIF (on 2nd death, ~53.53% marginal) | C19: =(925000+710000)*0.5353 -> 875215.5 | D19: Deferred until second death; full tax owing
B20: Deemed Disposition — Non-Registered Portfolio (50% inclusion) | C20: =NetWorthStatement!C11*0.5*0.5353 -> 388092.5 | D20: Capital gains triggered on death
B21: Life Insurance — Tax-Free Benefit | C21: =-2000000 -> -2000000 | D21: Reduces net tax burden on estate
B22: ESTIMATED NET ESTATE TAX EXPOSURE | C22: =SUM(C18:C21) -> -588617 | D22: Before planning strategies
B23: ESTATE PLANNING ACTION ITEMS
B24: Recommendation | C24: Priority | D24: Action Required
B25: Update Wills — Both James and Sarah | C25: URGENT | D25: Engage estate lawyer; mirror Wills with secondary beneficiaries as Emma and Liam
B26: Powers of Attorney — Personal Care & Property | C26: URGENT | D26: Execute POAs for both parties; designate backup attorney
B27: RRSP/RRIF Beneficiary Designations | C27: HIGH | D27: Confirm spouse as direct beneficiary; avoid estate designation to bypass probate
B28: Life Insurance — Annual Coverage Review | C28: HIGH | D28: Confirm $2M coverage aligns with income replacement, mortgage, and equalization goals
B29: Corporate Share Structure — Estate Freeze | C29: MEDIUM | D29: Engage corporate counsel for estate freeze on Sarah's law corp to facilitate future transfer
B30: Beneficiary Designation Annual Review | C30: HIGH | D30: Review all RRSP, TFSA, insurance, and corporate designations each year
