Workbook

Sheet Cover
B2: HNW CLIENT WEALTH PLAN
B3: Robert & Sandra Mitchell | Comprehensive Financial Plan | April 2025
B5: CLIENT OVERVIEW
B6: Clients | C6: Robert Mitchell (Age 52) & Sandra Mitchell (Age 49)
B7: Plan Date | C7: April 2025
B8: Prepared By | C8: Vatsal Chavda, BCom Finance — Seneca Polytechnic
B9: Planning Horizon | C9: 30 Years (to Age 82 / 79)
B10: Retirement Target | C10: Robert: Age 62 | Sandra: Age 60
B11: Primary Goals | C11: Retirement Income, Tax Efficiency, Estate Preservation
B14: KEY OUTCOMES
B15: Portfolio at Retirement | C15: 7710000
B16: Funding Ratio | C16: 105.5%
B17: Annual Retirement Income | C17: $320,000
B18: Annual Tax Savings | C18: $78,400
B19: Net Estate Value (Projected) | C19: $14,200,000
B20: Estate Coverage Ratio | C20: 142.0%
B23: WORKBOOK CONTENTS
B24: Assumptions | C24: All client inputs, rates, and planning parameters
B25: Portfolio | C25: Current allocation and 10-year projected growth
B26: Retirement Plan | C26: Income sources, CPP/OAS, and adequacy analysis
B27: Tax Plan | C27: RRSP/TFSA optimization and annual tax savings
B28: Estate Plan | C28: Net estate value, insurance, and liabilities
B29: Summary | C29: Consolidated overview and key recommendations

Sheet Assumptions
B1: ASSUMPTIONS & PLANNING PARAMETERS
B3: CLIENT PROFILE | E3: TAX & REGISTERED ACCOUNTS
B4: Robert — Current Age | C4: 52 | E4: Robert — Marginal Tax Rate | F4: 0.465
B5: Sandra — Current Age | C5: 49 | E5: Sandra — Marginal Tax Rate | F5: 0.435
B6: Robert — Retirement Age | C6: 62 | E6: CPP — Robert (at 65) | F6: 15000
B7: Sandra — Retirement Age | C7: 60 | E7: CPP — Sandra (at 65) | F7: 12000
B8: Planning Horizon | C8: 30 | E8: OAS — Both (at 65) | F8: 8500
B9: Robert — Current Salary | C9: 220000 | E9: RRSP Balance — Robert | F9: 680000
B10: Sandra — Current Salary | C10: 145000 | E10: RRSP Balance — Sandra | F10: 420000
B11: Annual Savings Rate | C11: 0.2 | E11: TFSA Balance — Robert | F11: 95000
E12: TFSA Balance — Sandra | F12: 88000
E13: Non-Reg. Portfolio | F13: 1917000
B14: PORTFOLIO ASSUMPTIONS
B15: Current Portfolio Value | C15: 3200000
B16: Expected Return (Pre-Retirement) | C16: 0.07 | E16: ESTATE PARAMETERS
B17: Expected Return (Post-Retirement) | C17: 0.055 | E17: Primary Residence Value | F17: 1800000
B18: Inflation Rate | C18: 0.025 | E18: Life Insurance — Robert | F18: 2000000
B19: Annual RRSP Contribution | C19: 31560 | E19: Life Insurance — Sandra | F19: 1500000
B20: Annual TFSA Contribution | C20: 7000 | E20: Other Real Estate | F20: 650000
B21: Annual Non-Reg. Contribution | C21: 50000 | E21: Outstanding Liabilities | F21: 420000
E22: Long-Term Estate Growth Rate | F22: 0.035

Sheet Portfolio
B1: PORTFOLIO ALLOCATION & PROJECTED GROWTH
B3: CURRENT ASSET ALLOCATION
B4: Asset Class | C4: Market Value ($) | D4: Allocation (%) | E4: Target (%) | F4: Variance (%)
B5: Canadian Equity | C5: 480000 | D5: =C5/SUM(C5:C12) -> 0.15 | E5: 0.15 | F5: =D5-E5 -> 0
B6: US Equity | C6: 768000 | D6: =C6/SUM(C5:C12) -> 0.24 | E6: 0.25 | F6: =D6-E6 -> -0.01
B7: International Equity | C7: 384000 | D7: =C7/SUM(C5:C12) -> 0.12 | E7: 0.1 | F7: =D7-E7 -> 0.02
B8: Canadian Fixed Income | C8: 640000 | D8: =C8/SUM(C5:C12) -> 0.2 | E8: 0.2 | F8: =D8-E8 -> 0
B9: Global Fixed Income | C9: 320000 | D9: =C9/SUM(C5:C12) -> 0.1 | E9: 0.1 | F9: =D9-E9 -> 0
B10: Real Estate (REITs) | C10: 256000 | D10: =C10/SUM(C5:C12) -> 0.08 | E10: 0.08 | F10: =D10-E10 -> 0
B11: Cash & Equivalents | C11: 192000 | D11: =C11/SUM(C5:C12) -> 0.06 | E11: 0.07 | F11: =D11-E11 -> -0.01
B12: Alternative Assets | C12: 160000 | D12: =C12/SUM(C5:C12) -> 0.05 | E12: 0.05 | F12: =D12-E12 -> 0
B13: TOTAL PORTFOLIO | C13: =SUM(C5:C12) -> 3200000 | D13: =SUM(D5:D12) -> 1 | E13: =SUM(E5:E12) -> 1
B15: 10-YEAR PROJECTED GROWTH TO RETIREMENT
B16: Year | C16: Beginning Value ($) | D16: Contributions ($) | E16: Growth ($) | F16: Ending Value ($)
B17: Year 1 | C17: =Assumptions!C15 -> 3200000 | D17: =(Assumptions!C19+Assumptions!C20+Assumptions!C21) -> 88560 | E17: =(C17+D17)*Assumptions!C16 -> 230199.2 | F17: =C17+D17+E17 -> 3518759.2
B18: Year 2 | C18: =F17 -> 3518759.2 | D18: =(Assumptions!C19+Assumptions!C20+Assumptions!C21) -> 88560 | E18: =(C18+D18)*Assumptions!C16 -> 252512.34 | F18: =C18+D18+E18 -> 3859831.5
B19: Year 3 | C19: =F18 -> 3859831.5 | D19: =(Assumptions!C19+Assumptions!C20+Assumptions!C21) -> 88560 | E19: =(C19+D19)*Assumptions!C16 -> 276387.41 | F19: =C19+D19+E19 -> 4224779
B20: Year 4 | C20: =F19 -> 4224779 | D20: =(Assumptions!C19+Assumptions!C20+Assumptions!C21) -> 88560 | E20: =(C20+D20)*Assumptions!C16 -> 301933.73 | F20: =C20+D20+E20 -> 4615272.7
B21: Year 5 | C21: =F20 -> 4615272.7 | D21: =(Assumptions!C19+Assumptions!C20+Assumptions!C21) -> 88560 | E21: =(C21+D21)*Assumptions!C16 -> 329268.29 | F21: =C21+D21+E21 -> 5033101
B22: Year 6 | C22: =F21 -> 5033101 | D22: =(Assumptions!C19+Assumptions!C20+Assumptions!C21) -> 88560 | E22: =(C22+D22)*Assumptions!C16 -> 358516.27 | F22: =C22+D22+E22 -> 5480177.2
B23: Year 7 | C23: =F22 -> 5480177.2 | D23: =(Assumptions!C19+Assumptions!C20+Assumptions!C21) -> 88560 | E23: =(C23+D23)*Assumptions!C16 -> 389811.61 | F23: =C23+D23+E23 -> 5958548.8
B24: Year 8 | C24: =F23 -> 5958548.8 | D24: =(Assumptions!C19+Assumptions!C20+Assumptions!C21) -> 88560 | E24: =(C24+D24)*Assumptions!C16 -> 423297.62 | F24: =C24+D24+E24 -> 6470406.5
B25: Year 9 | C25: =F24 -> 6470406.5 | D25: =(Assumptions!C19+Assumptions!C20+Assumptions!C21) -> 88560 | E25: =(C25+D25)*Assumptions!C16 -> 459127.65 | F25: =C25+D25+E25 -> 7018094.1
B26: Year 10 | C26: =F25 -> 7018094.1 | D26: =(Assumptions!C19+Assumptions!C20+Assumptions!C21) -> 88560 | E26: =(C26+D26)*Assumptions!C16 -> 497465.79 | F26: =C26+D26+E26 -> 7604119.9
B27: PORTFOLIO AT RETIREMENT (Year 10) | C27: =F26 -> 7604119.9

Sheet RetirementPlan
B1: RETIREMENT INCOME PLAN
B3: ANNUAL INCOME AT RETIREMENT
B4: Income Source | C4: Robert ($) | D4: Sandra ($) | E4: Combined ($)
B5: RRSP / RRIF Drawdown | C5: 95000 | D5: 65000 | E5: =C5+D5 -> 160000
B6: TFSA Withdrawals (Tax-Free) | C6: 28000 | D6: 24000 | E6: =C6+D6 -> 52000
B7: Non-Registered Portfolio | C7: 55000 | D7: 38000 | E7: =C7+D7 -> 93000
B8: CPP Benefits | C8: 15000 | D8: 12000 | E8: =C8+D8 -> 27000
B9: OAS Benefits | C9: 8500 | D9: 8500 | E9: =C9+D9 -> 17000
B10: Rental / Other Income | C10: 12000 | D10: 0 | E10: =C10+D10 -> 12000
B11: TOTAL ANNUAL INCOME | C11: =SUM(C5:C10) -> 213500 | D11: =SUM(D5:D10) -> 147500 | E11: =SUM(E5:E10) -> 361000
B13: INCOME ADEQUACY ANALYSIS
B14: Target Annual Retirement Income | C14: 320000
B15: Projected Annual Income | C15: =E11 -> 361000
B16: Annual Surplus / (Shortfall) | C16: =C15-C14 -> 41000
B17: Funding Ratio | C17: =C15/C14 -> 1.128125
B18: Portfolio Depletion Risk | C18: Low — projected income exceeds target by 7.5%

Sheet TaxPlan
B1: TAX OPTIMIZATION PLAN
B3: ANNUAL TAX SAVINGS BY STRATEGY
B4: Strategy | C4: Annual Savings ($) | D4: Notes
B5: Maximize RRSP Contributions | C5: 14700 | D5: Tax deduction at 46.5% marginal rate for Robert
B6: Spousal RRSP Income Splitting | C6: 8200 | D6: Shift income to Sandra at lower marginal rate
B7: TFSA Max Contribution (Both) | C7: 6500 | D7: Tax-free growth on $14,000 combined annually
B8: RRIF Minimum Drawdown Timing | C8: 12400 | D8: Defer RRSP conversion to age 71 to minimize tax
B9: CPP Deferral to Age 65 | C9: 18600 | D9: Maximize lifetime CPP benefit by deferring
B10: Non-Reg. Tax-Loss Harvesting | C10: 9800 | D10: Offset realized capital gains with portfolio losses
B11: Pension Income Splitting | C11: 8200 | D11: Split up to 50% of eligible pension income
B12: TOTAL ANNUAL TAX SAVINGS | C12: =SUM(C5:C11) -> 78400

Sheet EstatePlan
B1: ESTATE PLAN & NET ESTATE SUMMARY
B3: ESTATE ASSETS
B4: Item | C4: Current Value ($) | D4: Projected Value at Death ($)
B5: Investment Portfolio | C5: 3200000 | D5: =C5*(1+Assumptions!F22)^20 -> 6367324.4
B6: Primary Residence | C6: 1800000 | D6: =C6*(1+Assumptions!F22)^20 -> 3581620
B7: Other Real Estate | C7: 650000 | D7: =C7*(1+Assumptions!F22)^20 -> 1293362.8
B8: Life Insurance — Robert | C8: 2000000 | D8: =C8*(1+Assumptions!F22)^20 -> 3979577.7
B9: Life Insurance — Sandra | C9: 1500000 | D9: =C9*(1+Assumptions!F22)^20 -> 2984683.3
B10: RRSP / RRIF Assets | C10: 1100000 | D10: =C10*(1+Assumptions!F22)^20 -> 2188767.7
B11: TFSA Assets | C11: 183000 | D11: =C11*(1+Assumptions!F22)^20 -> 364131.36
B12: TOTAL GROSS ESTATE | C12: =SUM(C5:C11) -> 10433000 | D12: =SUM(D5:D11) -> 20759467
B14: LIABILITIES & ESTATE COSTS
B15: Item | C15: Current Value ($) | D15: Projected Value at Death ($)
B16: Outstanding Mortgage & Debt | C16: 420000 | D16: =C16*(1+Assumptions!F22)^20 -> 835711.32
B17: Estimated Probate Costs (1.5%) | C17: =C12*0.015 -> 156495 | D17: =D12*0.015 -> 311392.01
B18: Legal & Administrative Costs | C18: 45000 | D18: =C18*(1+Assumptions!F22)^20 -> 89540.499
B19: TOTAL LIABILITIES | C19: =SUM(C16:C18) -> 621495 | D19: =SUM(D16:D18) -> 1236643.8
B21: NET ESTATE VALUE | C21: =C12-C19 -> 9811505 | D21: =D12-D19 -> 19522823

Sheet Summary
B1: PLAN SUMMARY — CONSOLIDATED OVERVIEW
B4: PORTFOLIO
B5: Current Portfolio Value | C5: =Portfolio!C13 -> 3200000
B6: Projected Portfolio at Retirement | C6: =Portfolio!F26 -> 7604119.9
B7: Expected Annual Return (Pre-Ret.) | C7: =Assumptions!C16 -> 0.07
B8: Total Annual Contributions | C8: =Assumptions!C19+Assumptions!C20+Assumptions!C21 -> 88560
B10: RETIREMENT INCOME
B11: Target Annual Retirement Income | C11: =RetirementPlan!C14 -> 320000
B12: Projected Annual Income | C12: =RetirementPlan!C15 -> 361000
B13: Annual Surplus / (Shortfall) | C13: =RetirementPlan!C16 -> 41000
B14: Funding Ratio | C14: =RetirementPlan!C17 -> 1.128125
B16: TAX OPTIMIZATION
B17: Total Annual Tax Savings | C17: =TaxPlan!C12 -> 78400
B18: RRSP Balance — Robert | C18: =Assumptions!F9 -> 680000
B19: RRSP Balance — Sandra | C19: =Assumptions!F10 -> 420000
B20: Combined TFSA Balance | C20: =Assumptions!F11+Assumptions!F12 -> 183000
B22: ESTATE PLAN
B23: Total Gross Estate (Current) | C23: =EstatePlan!C12 -> 10433000
B24: Total Gross Estate (Projected) | C24: =EstatePlan!D12 -> 20759467
B25: Net Estate Value (Projected) | C25: =EstatePlan!D21 -> 19522823
B26: Total Life Insurance Coverage | C26: =Assumptions!F18+Assumptions!F19 -> 3500000
B28: KEY RECOMMENDATIONS
B29: 1. Maximize RRSP contributions annually — Robert's 46.5% marginal rate makes this the highest-priority tax shelter.
B30: 2. Execute spousal RRSP contributions each year to equalize retirement income and reduce combined tax liability.
B31: 3. Maximize TFSA contributions for both clients ($14,000 combined) — all growth and withdrawals are tax-free.
B32: 4. Defer CPP to age 65 for both clients — increases lifetime benefit by approximately 8.4% per year of deferral.
B33: 5. Initiate systematic tax-loss harvesting in the non-registered portfolio to offset realized capital gains.
B34: 6. Review life insurance coverage annually — current $3.5M combined coverage supports estate objectives.
B35: 7. Reduce equity allocation in Year 8 as retirement approaches — shift toward capital preservation.
