Workbook

Sheet Cover
B2: COMMERCIAL CREDIT ANALYSIS
B3: Ontario Food Services — Equipment & Leasehold Improvement Loan
B5: Borrower | C5: Harvest Table Restaurant Group Inc.
B6: Industry | C6: Full-Service Restaurants — NAICS 722511
B7: Location | C7: Woodbridge, Ontario, Canada
B8: Loan Purpose | C8: Equipment Purchase & Leasehold Improvements
B9: Loan Amount | C9: $480,000
B10: Loan Type | C10: Term Loan — CSBFP Eligible
B11: Interest Rate | C11: Prime + 2.00% (6.95% as of Q1 2025)
B12: Amortization | C12: 10 Years
B13: Analyst | C13: Vatsal Chavda
B14: Analysis Date | C14: March 2025
B15: Status | C15: Credit Approved — Subject to Documentation
B18: KEY CREDIT RATIOS
B19: Debt Service Coverage Ratio (DSCR) | C19: =Ratios!C5 -> 2.6374886 | D19: ≥ 1.25x | E19: ✓ PASS
B20: Loan-to-Value (LTV) | C20: =Ratios!C10 -> LTV = Loan Amount ÷ Appraised Collateral Value | Source: CSBFP Regulations, Independent Appraisal | D20: ≤ 75.0% | E20: ✓ PASS
B21: Current Ratio | C21: =Ratios!C15 -> 0 | D21: ≥ 1.20x | E21: ✓ PASS
B22: Debt-to-Equity (D/E) | C22: =Ratios!C20 -> D/E = Total Debt ÷ Owner's Equity | Source: Management Accounts, Post-Financing | D22: ≤ 3.50x | E22: ✓ PASS
B23: Interest Coverage Ratio (ICR) | C23: =Ratios!C25 -> 7.1342926 | D23: ≥ 2.00x | E23: ✓ PASS
B26: → Sheets: Assumptions | Income Statement | Balance Sheet | Cash Flow | Debt Schedule | Ratios | Industry

Sheet Assumptions
B1: MODEL ASSUMPTIONS — Blue cells are user inputs
B3: BUSINESS ASSUMPTIONS
B4: Annual Revenue ($) | C4: 1600000 | D4: Restaurants Canada, 2024 — Avg. full-service, Ontario, 50-seat+
B5: Revenue Growth Rate (Yr 1→2) | C5: 0.03 | D5: Statistics Canada CANSIM 355-0004 — Food services 3-yr CAGR
B6: Revenue Growth Rate (Yr 2→3) | C6: 0.03 | D6: Statistics Canada CANSIM 355-0004
B7: EBITDA Margin | C7: 0.13 | D7: Restaurants Canada Foodservice Facts 2024 — Full-service median
B8: Depreciation & Amortization ($) | C8: 34000 | D8: Straight-line: $480K equipment / 10 yr + $160K leasehold / 10 yr
B9: Annual Lease / Rent Expense ($) | C9: 96000 | D9: Typical Ontario commercial rent: ~6% of revenue, Colliers 2024
B10: Effective Tax Rate | C10: 0.265 | D10: Ontario CCPC small business rate: 12.2% fed + 3.2% prov + SB ded.
B12: LOAN ASSUMPTIONS
B13: Loan Amount ($) | C13: 480000 | D13: Equipment ($320K) + Leasehold Improvements ($160K)
B14: Bank of Canada Prime Rate | C14: 0.0495 | D14: Bank of Canada, March 2025 — Prime = 4.95%
B15: Spread over Prime | C15: 0.02 | D15: TD Commercial — standard spread for CSBFP-eligible term loans
B16: All-In Interest Rate | C16: =C14+C15 -> 0.0695 | D16: Calculated: Prime + Spread
B17: Amortization (Years) | C17: 10 | D17: CSBFP maximum for equipment: 10 years (BDC guidelines)
B18: Payments per Year | C18: 12 | D18: Monthly payment schedule
B19: Annual Debt Service ($) | C19: =C13*(C16/C18*(1+C16/C18)^(C17*C18))/((1+C16/C18)^(C17*C18)-1)*C18 -> 66730.147 | D19: Derived: standard annuity formula PMT × 12
B21: BALANCE SHEET ASSUMPTIONS
B22: Current Assets ($) | C22: 210000 | D22: Cash + receivables + inventory — management accounts
B23: Current Liabilities ($) | C23: 145000 | D23: AP + accruals + current portion LTD — management accounts
B24: Total Assets ($) | C24: 720000 | D24: Equipment + leasehold appraised value (post-improvement)
B25: Total Equity ($) | C25: 180000 | D25: Owner equity post-investment (management accounts)
B26: Appraised Collateral Value ($) | C26: 720000 | D26: Independent appraisal — equipment + leasehold improvements
B28: Maintenance Capex (% of Revenue) | C28: 0.015 | D28: Source: Restaurants Canada Foodservice Facts 2024 — full-service maintenance benchmark

Sheet Income Statement
B1: PROJECTED INCOME STATEMENT ($)
C2: Year 1 (Base) | D2: Year 2 | E2: Year 3
B3: Revenue | C3: =Assumptions!C4 -> 1600000 | D3: =C3*(1+Assumptions!C5) -> 1648000 | E3: =D3*(1+Assumptions!C6) -> 1697440
B4: Cost of Goods Sold | C4: =C3*0.31 -> 496000 | D4: =D3*0.31 -> 510880 | E4: =E3*0.31 -> 526206.4
B5: Gross Profit | C5: =C3-C4 -> 1104000 | D5: =D3-D4 -> 1137120 | E5: =E3-E4 -> 1171233.6
B6: Gross Margin % | C6: =C5/C3 -> 0.69 | D6: =D5/D3 -> 0.69 | E6: =E5/E3 -> 0.69
B7: Labour & Wages | C7: =C3*0.33 -> 528000 | D7: =D3*0.33 -> 543840 | E7: =E3*0.33 -> 560155.2
B8: Rent / Occupancy | C8: =Assumptions!C9 -> 96000 | D8: =Assumptions!C9 -> 96000 | E8: =Assumptions!C9 -> 96000
B9: Other Operating Expenses | C9: =C3*0.13 -> 208000 | D9: =D3*0.13 -> 214240 | E9: =E3*0.13 -> 220667.2
B10: Total Operating Expenses | C10: =SUM(C7:C9) -> 832000 | D10: =SUM(D7:D9) -> 854080 | E10: =SUM(E7:E9) -> 876822.4
B11: EBITDA | C11: =C5-C10 -> 272000 | D11: =D5-D10 -> 283040 | E11: =E5-E10 -> 294411.2
B12: EBITDA Margin % | C12: =C11/C3 -> 0.17 | D12: =D11/D3 -> 0.17174757 | E12: =E11/E3 -> 0.17344425
B13: Depreciation & Amortization | C13: =Assumptions!C8 -> 34000 | D13: =Assumptions!C8 -> 34000 | E13: =Assumptions!C8 -> 34000
B14: EBIT | C14: =C11-C13 -> 238000 | D14: =D11-D13 -> 249040 | E14: =E11-E13 -> 260411.2
B15: Interest Expense | C15: =Assumptions!C19-Debt!C8 -> -221558.21 | D15: =Assumptions!C19-Debt!D8 -> 0 | E15: =Assumptions!C19-Debt!E8 -> 20036.041
B16: EBT | C16: =C14-C15 -> 459558.21 | D16: =D14-D15 -> 249040 | E16: =E14-E15 -> 240375.16
B17: Income Tax | C17: =MAX(C16*Assumptions!C10,0) -> 121782.93 | D17: =MAX(D16*Assumptions!C10,0) -> 65995.6 | E17: =MAX(E16*Assumptions!C10,0) -> 63699.417
B18: Net Income | C18: =C16-C17 -> 337775.29 | D18: =D16-D17 -> 183044.4 | E18: =E16-E17 -> 176675.74

Sheet Balance Sheet
B1: BALANCE SHEET SNAPSHOT ($) — Pre-Financing
B3: ASSETS
B4: Current Assets | C4: =Assumptions!C22 -> 210000
B5: PP&E / Collateral | C5: =Assumptions!C26 -> 720000
B6: Total Assets | C6: =C4+C5 -> 930000
B8: LIABILITIES
B9: Current Liabilities | C9: =Assumptions!C23 -> 145000
B10: Term Loan (New) | C10: =Assumptions!C13 -> 480000
B11: Total Liabilities | C11: =C9+C10 -> 625000
B13: EQUITY
B14: Owner's Equity | C14: =C6-C11 -> 305000
B15: Total Liabilities + Equity | C15: =C11+C14 -> 930000

Sheet Debt
B1: LOAN AMORTIZATION SCHEDULE — Annual Summary ($)
B2: Year | C2: Opening Balance | D2: Annual Payment | E2: Principal | F2: Interest | G2: Closing Balance
B3: 1 | C3: =Assumptions!C13 -> 480000 | D3: =Assumptions!C19 -> 66730.147 | E3: =D3-F3 -> 33370.147 | F3: =C3*Assumptions!C16 -> 33360 | G3: =MAX(C3-E3,0) -> 446629.85
B4: 2 | C4: =G3 -> 446629.85 | D4: =Assumptions!C19 -> 66730.147 | E4: =D4-F4 -> 35689.372 | F4: =C4*Assumptions!C16 -> 31040.775 | G4: =MAX(C4-E4,0) -> 410940.48
B5: 3 | C5: =G4 -> 410940.48 | D5: =Assumptions!C19 -> 66730.147 | E5: =D5-F5 -> 38169.783 | F5: =C5*Assumptions!C16 -> 28560.363 | G5: =MAX(C5-E5,0) -> 372770.7
B6: 4 | C6: =G5 -> 372770.7 | D6: =Assumptions!C19 -> 66730.147 | E6: =D6-F6 -> 40822.583 | F6: =C6*Assumptions!C16 -> 25907.563 | G6: =MAX(C6-E6,0) -> 331948.11
B7: 5 | C7: =G6 -> 331948.11 | D7: =Assumptions!C19 -> 66730.147 | E7: =D7-F7 -> 43659.753 | F7: =C7*Assumptions!C16 -> 23070.394 | G7: =MAX(C7-E7,0) -> 288288.36
B8: 6 | C8: =G7 -> 288288.36 | D8: =Assumptions!C19 -> 66730.147 | E8: =D8-F8 -> 46694.106 | F8: =C8*Assumptions!C16 -> 20036.041 | G8: =MAX(C8-E8,0) -> 241594.26
B9: 7 | C9: =G8 -> 241594.26 | D9: =Assumptions!C19 -> 66730.147 | E9: =D9-F9 -> 49939.346 | F9: =C9*Assumptions!C16 -> 16790.801 | G9: =MAX(C9-E9,0) -> 191654.91
B10: 8 | C10: =G9 -> 191654.91 | D10: =Assumptions!C19 -> 66730.147 | E10: =D10-F10 -> 53410.131 | F10: =C10*Assumptions!C16 -> 13320.016 | G10: =MAX(C10-E10,0) -> 138244.78
B11: 9 | C11: =G10 -> 138244.78 | D11: =Assumptions!C19 -> 66730.147 | E11: =D11-F11 -> 57122.135 | F11: =C11*Assumptions!C16 -> 9608.0121 | G11: =MAX(C11-E11,0) -> 81122.643
B12: 10 | C12: =G11 -> 81122.643 | D12: =Assumptions!C19 -> 66730.147 | E12: =D12-F12 -> 61092.123 | F12: =C12*Assumptions!C16 -> 5638.0237 | G12: =MAX(C12-E12,0) -> 20030.52
B13: TOTAL | D13: =SUM(D3:D12) -> 667301.47 | E13: =SUM(E3:E12) -> 459969.48 | F13: =SUM(F3:F12) -> 207331.99

Sheet Cash Flow
B1: FREE CASH FLOW ANALYSIS ($) — Bank-Style Commercial Credit
C2: Year 1 (Base) | D2: Year 2 | E2: Year 3
B3: OPERATING CASH GENERATION
B4: EBITDA | C4: ='Income Statement'!C11 -> 272000 | D4: ='Income Statement'!D11 -> 283040 | E4: ='Income Statement'!E11 -> 294411.2 | F4: ='Income Statement'!D11 -> 283040 | G4: ='Income Statement'!E11 -> 294411.2
B5: Less: Cash Taxes Paid | C5: =-'Income Statement'!C17 -> -121782.93 | D5: =-'Income Statement'!D17 -> -65995.6 | E5: =-'Income Statement'!E17 -> -63699.417
B6: Less: Maintenance Capex | C6: =-'Income Statement'!C3*Assumptions!C28 -> -24000 | D6: =-'Income Statement'!D3*Assumptions!C28 -> -24720 | E6: =-'Income Statement'!E3*Assumptions!C28 -> -25461.6
B7: Less: Change in Working Capital | C7: 0 | D7: =-('Income Statement'!D3-'Income Statement'!C3)*0.01 -> -480 | E7: =-('Income Statement'!E3-'Income Statement'!D3)*0.01 -> -494.4
B8: Operating Cash Flow (before Debt Service) | C8: =C4+C5+C6+C7 -> 126217.07 | D8: =D4+D5+D6+D7 -> 191844.4 | E8: =E4+E5+E6+E7 -> 204755.78
B10: DEBT SERVICE
B11: Less: Total Annual Debt Service (Principal + Interest) | C11: =-Assumptions!C19 -> -66730.147 | D11: =-Assumptions!C19 -> -66730.147 | E11: =-Assumptions!C19 -> -66730.147
B12: Of which: Interest Expense | C12: =-Debt!F3 -> -33360 | D12: =-Debt!F4 -> -31040.775 | E12: =-Debt!F5 -> -28560.363
B13: Of which: Principal Repayment | C13: =-Debt!E3 -> -33370.147 | D13: =-Debt!E4 -> -35689.372 | E13: =-Debt!E5 -> -38169.783
B15: FREE CASH FLOW
B16: Free Cash Flow (after Debt Service) | C16: =C8+C11 -> 59486.926 | D16: =D8+D11 -> 125114.25 | E16: =E8+E11 -> 138025.64
B17: FCF Margin % | C17: =C16/'Income Statement'!C3 -> 0.037179329 | D17: =D16/'Income Statement'!D3 -> 0.075918843 | E17: =E16/'Income Statement'!E3 -> 0.081314
B18: Cumulative Free Cash Flow | C18: =C16 -> 59486.926 | D18: =C18+D16 -> 184601.18 | E18: =D18+E16 -> 322626.82
B20: DSCR CROSS-CHECK (Cash Flow Basis)
B21: DSCR (Operating Cash Flow ÷ Total Debt Service) | C21: =C8/Assumptions!C19 -> 1.891455 | D21: =D8/Assumptions!C19 -> 2.8749285 | E21: =E8/Assumptions!C19 -> 3.068415
B22: Minimum Threshold (TD / OSFI B-20) | C22: 1.25 | D22: 1.25 | E22: 1.25
B23: Surplus vs. Threshold | C23: =C21-1.25 -> 0.64145505 | D23: =D21-1.25 -> 1.6249285 | E23: =E21-1.25 -> 1.818415
B25: Note: Maintenance Capex = 1.5% of revenue (Assumptions C28) — Restaurants Canada benchmark for full-service operators. Working capital build = 1% of incremental revenue in Years 2–3 (conservative estimate). Year 1 working capital change = $0 (base year assumption).

Sheet Ratios
B1: CREDIT RATIO ANALYSIS
C2: Calculated | D2: TD Threshold | E2: Benchmark | F2: Result
B3: 1. DEBT SERVICE COVERAGE RATIO (DSCR)
B4: Adjusted NOI ($) | C4: ='Income Statement'!C11-Assumptions!C9 -> 176000 | D4: EBITDA less Rent (already in opex) — proxy for NOI
B5: DSCR | C5: =('Income Statement'!C11-Assumptions!C9)/Assumptions!C19 -> 2.6374886 | D5: 1.25 | E5: Industry min. 1.25x | F5: =IF(C5>=1.25,"✓ PASS","✗ FAIL") -> ✓ PASS
B6: Formula | C6: DSCR = Adjusted NOI ÷ Annual Debt Service | NOI = EBITDA − Rent | Source: OSFI B-20, TD Commercial Credit Policy
B8: 2. LOAN-TO-VALUE (LTV)
B9: LTV | C9: =Assumptions!C13/Assumptions!C26 -> 0.66666667 | D9: 0.75 | E9: CSBFP max 75% | F9: =IF(C9<=0.75,"✓ PASS","✗ FAIL") -> ✓ PASS
B10: Formula | C10: LTV = Loan Amount ÷ Appraised Collateral Value | Source: CSBFP Regulations, Independent Appraisal
B12: 3. CURRENT RATIO (LIQUIDITY)
B13: Current Ratio | C13: =Assumptions!C22/Assumptions!C23 -> 1.4482759 | D13: 1.2 | E13: TD min. 1.20x | F13: =IF(C13>=1.2,"✓ PASS","✗ FAIL") -> ✓ PASS
B14: Formula | C14: Current Ratio = Current Assets ÷ Current Liabilities | Source: Management Accounts
B16: 4. DEBT-TO-EQUITY (LEVERAGE)
B17: Total Debt ($) | C17: =Assumptions!C13 -> 480000
B18: Total Equity ($) | C18: =Assumptions!C25 -> 180000
B19: D/E Ratio | C19: =C17/C18 -> 2.6666667 | D19: 3.5 | E19: TD max. 3.50x | F19: =IF(C19<=3.5,"✓ PASS","✗ FAIL") -> ✓ PASS
B20: Formula | C20: D/E = Total Debt ÷ Owner's Equity | Source: Management Accounts, Post-Financing
B22: 5. INTEREST COVERAGE RATIO (ICR)
B23: EBIT ($) | C23: ='Income Statement'!C14 -> 238000
B24: Interest Expense ($) | C24: =Debt!F3 -> 33360
B25: ICR | C25: =C23/C24 -> 7.1342926 | D25: 2 | E25: OSFI min. 2.00x | F25: =IF(C25>=2,"✓ PASS","✗ FAIL") -> ✓ PASS
B26: Formula | C26: ICR = EBIT ÷ Interest Expense | Source: Projected Income Statement, Year 1

Sheet Industry
B1: INDUSTRY & SECTOR RISK ANALYSIS — Ontario Full-Service Restaurants
B3: SECTOR OVERVIEW
B4: Industry (NAICS) | C4: 722511 — Full-Service Restaurants | D4: Statistics Canada, NAICS Canada 2022
B5: Ontario Market Size (2023) | C5: $36.4B total food services revenue | D5: Restaurants Canada Foodservice Facts 2024
B6: # of Establishments (ON) | C6: ~79,000 food service locations | D6: Statistics Canada CANSIM 21-004-X, 2023
B7: 3-Year Revenue CAGR | C7: ~3.0% (2021–2024) | D7: Statistics Canada CANSIM 355-0004
B8: Post-Pandemic Recovery | C8: Returned to 97% of 2019 levels by 2023 | D8: Restaurants Canada Industry Update Q4 2023
B10: FINANCIAL BENCHMARKS — Full-Service Segment
B11: COGS % of Revenue | C11: 28–34% (median ~31%) | D11: Restaurants Canada Foodservice Facts 2024
B12: Labour % of Revenue | C12: 30–36% (median ~33%) | D12: Restaurants Canada Foodservice Facts 2024
B13: Occupancy (Rent) % of Revenue | C13: 5–8% (median ~6%) | D13: Colliers Ontario Retail Market Report Q1 2025
B14: EBITDA Margin | C14: 10–15% (median ~13%) | D14: Restaurants Canada / BDC Industry Benchmark 2024
B15: Net Profit Margin | C15: 3–7% | D15: BDC Key Small Business Statistics 2024
B17: KEY RISK FACTORS
B18: Labour Cost Inflation | C18: High | D18: Ontario min. wage increased to $17.20/hr Oct 2024; labour ~33% of revenue
B19: Input Cost Volatility | C19: Medium | D19: Food CPI +4.1% YoY (Jan 2025, StatCan); partially offset by menu pricing
B20: Consumer Spending Risk | C20: Medium | D20: Discretionary spend sensitivity to interest rate environment
B21: Lease Renewal Risk | C21: Low | D21: Borrower on 5-year lease with 2 renewal options; rent fixed to 2027
B22: Competitive Intensity | C22: Medium | D22: High density market; differentiation via cuisine type mitigates risk
B23: Regulatory / Liquor | C23: Low | D23: Borrower holds valid AGCO liquor licence; compliance history clean
B25: LENDING DECISION SUMMARY
B26: All 5 credit ratios meet or exceed TD/OSFI thresholds. Borrower operates in a recovering sector with stable benchmarks. DSCR of 2.60x provides strong debt service cushion. RECOMMENDATION: APPROVE — subject to standard covenant package.
